Workbook

Sheet DASHBOARD
B2: 🚗 SPIDERVO PRO — Gestion de Véhicules d'Occasion
B3: Tableau de bord professionnel — Mis à jour automatiquement
B5: 📦 INDICATEURS STOCK
B7: 📦 VÉHICULES EN STOCK | C7: 💰 VALEUR STOCK | E7: 📈 MARGE POTENTIELLE | F7: 🏷️ PRIX MOYEN | H7: ⏳ VÉHICULES DORMANTS | I7: 🔧 EN PRÉPARATION
B8: =COUNTIFS('STOCK VO'!L3:L5002,"<>Vendu",'STOCK VO'!L3:L5002,"<>Livré",'STOCK VO'!L3:L5002,"<>") -> 0 | C8: =SUMPRODUCT(('STOCK VO'!L3:L5002<>"Vendu")*('STOCK VO'!L3:L5002<>"Livré")*('STOCK VO'!L3:L5002<>"")*('STOCK VO'!AH3:AH5002)) -> 0 | E8: =IFERROR(SUMPRODUCT(('STOCK VO'!L3:L5002<>"Vendu")*('STOCK VO'!L3:L5002<>"Livré")*('STOCK VO'!L3:L5002<>"")*('STOCK VO'!AL3:AL5002)),0) -> 0 | F8: =IFERROR(AVERAGEIF('STOCK VO'!L3:L5002,"Publié",'STOCK VO'!AH3:AH5002),0) -> 0 | H8: =COUNTIFS('STOCK VO'!L3:L5002,"<>Vendu",'STOCK VO'!L3:L5002,"<>Livré",'STOCK VO'!L3:L5002,"<>",'STOCK VO'!AR3:AR5002,">45") -> 0 | I8: =COUNTIF('STOCK VO'!L3:L5002,"Préparation") -> 0
B9: vs mois précédent | C9: vs mois précédent | E9: vs mois précédent | F9: vs mois précédent | H9: vs mois précédent | I9: vs mois précédent
B11: 💰 PERFORMANCE COMMERCIALE DU MOIS
B13: 🛒 VENDUS CE MOIS | C13: 💵 CA MENSUEL | E13: 💎 MARGE NETTE | F13: 📊 TAUX DE MARGE | H13: 🔥 LEADS ACTIFS | I13: 📋 DOSSIERS INCOMPLETS
B14: =COUNTIFS(VENTES!E2:E5001,">="&DATE(YEAR(TODAY()),MONTH(TODAY()),1),VENTES!E2:E5001,"<="&EOMONTH(TODAY(),0)) -> 0 | C14: =SUMPRODUCT((VENTES!E2:E5001>=DATE(YEAR(TODAY()),MONTH(TODAY()),1))*(VENTES!E2:E5001<=EOMONTH(TODAY(),0))*(VENTES!I2:I5001)) -> 0 | E14: =IFERROR(SUMPRODUCT((VENTES!E2:E5001>=DATE(YEAR(TODAY()),MONTH(TODAY()),1))*(VENTES!E2:E5001<=EOMONTH(TODAY(),0))*(VENTES!M2:M5001)),0) -> 0 | F14: =IFERROR(SUMPRODUCT((VENTES!E2:E5001>=DATE(YEAR(TODAY()),MONTH(TODAY()),1))*(VENTES!E2:E5001<=EOMONTH(TODAY(),0))*(VENTES!M2:M5001))/SUMPRODUCT((VENTES!E2:E5001>=DATE(YEAR(TODAY()),MONTH(TODAY()),1))*(VENTES!E2:E5001<=EOMONTH(TODAY(),0))*(VENTES!I2:I5001)),0) -> 0 | H14: =COUNTIFS('CRM CLIENTS'!H2:H5001,"<>Vendu",'CRM CLIENTS'!H2:H5001,"<>Perdu",'CRM CLIENTS'!H2:H5001,"<>") -> 0 | I14: =COUNTIF(ADMINISTRATIF!P2:P5001,"⚠️ INCOMPLET")+COUNTIF(ADMINISTRATIF!P2:P5001,"❌ BLOQUANT") -> 0
B15: vs mois précédent | C15: vs mois précédent | E15: vs mois précédent | F15: vs mois précédent | H15: vs mois précédent | I15: vs mois précédent
B17: NAVIGATION RAPIDE
B18: 📦 STOCK VO | E18: 👥 CRM CLIENTS | F18: 💰 VENTES | H18: 📄 ADMINISTRATIF / FINANCE
B20: SpiderVO Pro v3.0 | Système de gestion VO professionnel | © 2024

Sheet STOCK VO
A1: IDENTIFICATION | M1: CARACTÉRISTIQUES | W1: ACHAT | AF1: CALCULS | AO1: VENTE | AR1: INFO
A2: ID Dossier | B2: Immatriculation | C2: VIN | D2: Marque | E2: Modèle | F2: Version | G2: Finition | H2: Année | I2: Kilométrage | J2: Carburant | K2: Boîte | L2: STATUT | M2: Puissance fisc. | N2: Date MEC | O2: Couleur | P2: Date Achat | Q2: Nb Clés | R2: Nb Propriétaires | S2: Historique Entretien | T2: Crit'Air | U2: CT Validité | V2: Garantie (mois) | W2: Provenance | X2: Fournisseur | Y2: Prix Achat | Z2: Frais Transport | AA2: Réparations | AB2: Nettoyage | AC2: Carte Grise | AD2: Préparation | AE2: Divers | AF2: Coût de Revient | AG2: Prix Conseillé | AH2: Prix Affiché | AI2: Prix Mini Acceptable | AJ2: Marge Brute € | AK2: Marge Brute % | AL2: Marge Nette € | AM2: TVA/Marge | AN2: ROI % | AO2: Date Vente | AP2: Prix Vente | AQ2: Client | AR2: Jours en Stock | AS2: Notes
AF3: =IF(A3="","",SUM(Y3:AE3)) | AG3: =IF(AF3="","",ROUND(AF3*1.2/100,0)*100) | AI3: =IF(AF3="","",ROUND(AF3*1.05/100,0)*100) | AJ3: =IF(OR(AH3="",AF3=""),"",AH3-AF3) | AK3: =IF(OR(AF3="",AF3=0),"",AJ3/AF3) | AL3: =IF(AJ3="","",AJ3-AM3) | AM3: =IF(OR(AH3="",AF3=""),"",ROUND((AH3-AF3)/1.2*0.2,2)) | AN3: =IF(OR(AF3="",AF3=0),"",AL3/AF3) | AR3: =IF(OR(A3="",P3=""),"",IF(AO3<>"",AO3-P3,TODAY()-P3))
AF4: =IF(A4="","",SUM(Y4:AE4)) | AG4: =IF(AF4="","",ROUND(AF4*1.2/100,0)*100) | AI4: =IF(AF4="","",ROUND(AF4*1.05/100,0)*100) | AJ4: =IF(OR(AH4="",AF4=""),"",AH4-AF4) | AK4: =IF(OR(AF4="",AF4=0),"",AJ4/AF4) | AL4: =IF(AJ4="","",AJ4-AM4) | AM4: =IF(OR(AH4="",AF4=""),"",ROUND((AH4-AF4)/1.2*0.2,2)) | AN4: =IF(OR(AF4="",AF4=0),"",AL4/AF4) | AR4: =IF(OR(A4="",P4=""),"",IF(AO4<>"",AO4-P4,TODAY()-P4))
AF5: =IF(A5="","",SUM(Y5:AE5)) | AG5: =IF(AF5="","",ROUND(AF5*1.2/100,0)*100) | AI5: =IF(AF5="","",ROUND(AF5*1.05/100,0)*100) | AJ5: =IF(OR(AH5="",AF5=""),"",AH5-AF5) | AK5: =IF(OR(AF5="",AF5=0),"",AJ5/AF5) | AL5: =IF(AJ5="","",AJ5-AM5) | AM5: =IF(OR(AH5="",AF5=""),"",ROUND((AH5-AF5)/1.2*0.2,2)) | AN5: =IF(OR(AF5="",AF5=0),"",AL5/AF5) | AR5: =IF(OR(A5="",P5=""),"",IF(AO5<>"",AO5-P5,TODAY()-P5))
AF6: =IF(A6="","",SUM(Y6:AE6)) | AG6: =IF(AF6="","",ROUND(AF6*1.2/100,0)*100) | AI6: =IF(AF6="","",ROUND(AF6*1.05/100,0)*100) | AJ6: =IF(OR(AH6="",AF6=""),"",AH6-AF6) | AK6: =IF(OR(AF6="",AF6=0),"",AJ6/AF6) | AL6: =IF(AJ6="","",AJ6-AM6) | AM6: =IF(OR(AH6="",AF6=""),"",ROUND((AH6-AF6)/1.2*0.2,2)) | AN6: =IF(OR(AF6="",AF6=0),"",AL6/AF6) | AR6: =IF(OR(A6="",P6=""),"",IF(AO6<>"",AO6-P6,TODAY()-P6))
AF7: =IF(A7="","",SUM(Y7:AE7)) | AG7: =IF(AF7="","",ROUND(AF7*1.2/100,0)*100) | AI7: =IF(AF7="","",ROUND(AF7*1.05/100,0)*100) | AJ7: =IF(OR(AH7="",AF7=""),"",AH7-AF7) | AK7: =IF(OR(AF7="",AF7=0),"",AJ7/AF7) | AL7: =IF(AJ7="","",AJ7-AM7) | AM7: =IF(OR(AH7="",AF7=""),"",ROUND((AH7-AF7)/1.2*0.2,2)) | AN7: =IF(OR(AF7="",AF7=0),"",AL7/AF7) | AR7: =IF(OR(A7="",P7=""),"",IF(AO7<>"",AO7-P7,TODAY()-P7))
AF8: =IF(A8="","",SUM(Y8:AE8)) | AG8: =IF(AF8="","",ROUND(AF8*1.2/100,0)*100) | AI8: =IF(AF8="","",ROUND(AF8*1.05/100,0)*100) | AJ8: =IF(OR(AH8="",AF8=""),"",AH8-AF8) | AK8: =IF(OR(AF8="",AF8=0),"",AJ8/AF8) | AL8: =IF(AJ8="","",AJ8-AM8) | AM8: =IF(OR(AH8="",AF8=""),"",ROUND((AH8-AF8)/1.2*0.2,2)) | AN8: =IF(OR(AF8="",AF8=0),"",AL8/AF8) | AR8: =IF(OR(A8="",P8=""),"",IF(AO8<>"",AO8-P8,TODAY()-P8))
AF9: =IF(A9="","",SUM(Y9:AE9)) | AG9: =IF(AF9="","",ROUND(AF9*1.2/100,0)*100) | AI9: =IF(AF9="","",ROUND(AF9*1.05/100,0)*100) | AJ9: =IF(OR(AH9="",AF9=""),"",AH9-AF9) | AK9: =IF(OR(AF9="",AF9=0),"",AJ9/AF9) | AL9: =IF(AJ9="","",AJ9-AM9) | AM9: =IF(OR(AH9="",AF9=""),"",ROUND((AH9-AF9)/1.2*0.2,2)) | AN9: =IF(OR(AF9="",AF9=0),"",AL9/AF9) | AR9: =IF(OR(A9="",P9=""),"",IF(AO9<>"",AO9-P9,TODAY()-P9))
AF10: =IF(A10="","",SUM(Y10:AE10)) | AG10: =IF(AF10="","",ROUND(AF10*1.2/100,0)*100) | AI10: =IF(AF10="","",ROUND(AF10*1.05/100,0)*100) | AJ10: =IF(OR(AH10="",AF10=""),"",AH10-AF10) | AK10: =IF(OR(AF10="",AF10=0),"",AJ10/AF10) | AL10: =IF(AJ10="","",AJ10-AM10) | AM10: =IF(OR(AH10="",AF10=""),"",ROUND((AH10-AF10)/1.2*0.2,2)) | AN10: =IF(OR(AF10="",AF10=0),"",AL10/AF10) | AR10: =IF(OR(A10="",P10=""),"",IF(AO10<>"",AO10-P10,TODAY()-P10))
AF11: =IF(A11="","",SUM(Y11:AE11)) | AG11: =IF(AF11="","",ROUND(AF11*1.2/100,0)*100) | AI11: =IF(AF11="","",ROUND(AF11*1.05/100,0)*100) | AJ11: =IF(OR(AH11="",AF11=""),"",AH11-AF11) | AK11: =IF(OR(AF11="",AF11=0),"",AJ11/AF11) | AL11: =IF(AJ11="","",AJ11-AM11) | AM11: =IF(OR(AH11="",AF11=""),"",ROUND((AH11-AF11)/1.2*0.2,2)) | AN11: =IF(OR(AF11="",AF11=0),"",AL11/AF11) | AR11: =IF(OR(A11="",P11=""),"",IF(AO11<>"",AO11-P11,TODAY()-P11))
AF12: =IF(A12="","",SUM(Y12:AE12)) | AG12: =IF(AF12="","",ROUND(AF12*1.2/100,0)*100) | AI12: =IF(AF12="","",ROUND(AF12*1.05/100,0)*100) | AJ12: =IF(OR(AH12="",AF12=""),"",AH12-AF12) | AK12: =IF(OR(AF12="",AF12=0),"",AJ12/AF12) | AL12: =IF(AJ12="","",AJ12-AM12) | AM12: =IF(OR(AH12="",AF12=""),"",ROUND((AH12-AF12)/1.2*0.2,2)) | AN12: =IF(OR(AF12="",AF12=0),"",AL12/AF12) | AR12: =IF(OR(A12="",P12=""),"",IF(AO12<>"",AO12-P12,TODAY()-P12))
AF13: =IF(A13="","",SUM(Y13:AE13)) | AG13: =IF(AF13="","",ROUND(AF13*1.2/100,0)*100) | AI13: =IF(AF13="","",ROUND(AF13*1.05/100,0)*100) | AJ13: =IF(OR(AH13="",AF13=""),"",AH13-AF13) | AK13: =IF(OR(AF13="",AF13=0),"",AJ13/AF13) | AL13: =IF(AJ13="","",AJ13-AM13) | AM13: =IF(OR(AH13="",AF13=""),"",ROUND((AH13-AF13)/1.2*0.2,2)) | AN13: =IF(OR(AF13="",AF13=0),"",AL13/AF13) | AR13: =IF(OR(A13="",P13=""),"",IF(AO13<>"",AO13-P13,TODAY()-P13))
AF14: =IF(A14="","",SUM(Y14:AE14)) | AG14: =IF(AF14="","",ROUND(AF14*1.2/100,0)*100) | AI14: =IF(AF14="","",ROUND(AF14*1.05/100,0)*100) | AJ14: =IF(OR(AH14="",AF14=""),"",AH14-AF14) | AK14: =IF(OR(AF14="",AF14=0),"",AJ14/AF14) | AL14: =IF(AJ14="","",AJ14-AM14) | AM14: =IF(OR(AH14="",AF14=""),"",ROUND((AH14-AF14)/1.2*0.2,2)) | AN14: =IF(OR(AF14="",AF14=0),"",AL14/AF14) | AR14: =IF(OR(A14="",P14=""),"",IF(AO14<>"",AO14-P14,TODAY()-P14))
... AF502: =IF(A502="","",SUM(Y502:AE502)) | AG502: =IF(AF502="","",ROUND(AF502*1.2/100,0)*100) | AI502: =IF(AF502="","",ROUND(AF502*1.05/100,0)*100) | AJ502: =IF(OR(AH502="",AF502=""),"",AH502-AF502) | AK502: =IF(OR(AF502="",AF502=0),"",AJ502/AF502) | AL502: =IF(AJ502="","",AJ502-AM502) | AM502: =IF(OR(AH502="",AF502=""),"",ROUND((AH502-AF502)/1.2*0.2,2)) | AN502: =IF(OR(AF502="",AF502=0),"",AL502/AF502) | AR502: =IF(OR(A502="",P502=""),"",IF(AO502<>"",AO502-P502,TODAY()-P502))

Sheet CRM CLIENTS
A1: ID Client | B1: Nom Prénom | C1: Téléphone | D1: Email | E1: Ville | F1: Source | G1: Véhicule Recherché | H1: STATUT PIPELINE | I1: Score | J1: Budget Max | K1: Date Entrée | L1: Dernier Contact | M1: Prochain RDV | N1: Nb Contacts | O1: Véhicule Attribué | P1: Vendeur | Q1: Notes / Historique | R1: Relance Auto | S1: Priorité

Sheet VENTES
A1: N° Commande | B1: N° Facture | C1: ID Dossier VO | D1: Client | E1: Date Vente | F1: Date Livraison | G1: Véhicule | H1: Immatriculation | I1: Prix Vente TTC | J1: Prix Vente HT | K1: Coût Revient | L1: Marge Brute € | M1: Marge Nette € | N1: TVA Marge | O1: Marge % | P1: Mode Paiement | Q1: Reprise | R1: Valeur Reprise | S1: Financement | T1: Garantie Vendue | U1: Prix Garantie | V1: Statut | W1: Vendeur | X1: Notes
J2: =IF(I2="","",ROUND(I2/1.2,2)) | L2: =IF(OR(I2="",K2=""),"",I2-K2) | M2: =IF(L2="","",L2-N2) | N2: =IF(L2="","",ROUND(L2/6,2)) | O2: =IF(OR(K2="",K2=0),"",M2/K2)
J3: =IF(I3="","",ROUND(I3/1.2,2)) | L3: =IF(OR(I3="",K3=""),"",I3-K3) | M3: =IF(L3="","",L3-N3) | N3: =IF(L3="","",ROUND(L3/6,2)) | O3: =IF(OR(K3="",K3=0),"",M3/K3)
J4: =IF(I4="","",ROUND(I4/1.2,2)) | L4: =IF(OR(I4="",K4=""),"",I4-K4) | M4: =IF(L4="","",L4-N4) | N4: =IF(L4="","",ROUND(L4/6,2)) | O4: =IF(OR(K4="",K4=0),"",M4/K4)
J5: =IF(I5="","",ROUND(I5/1.2,2)) | L5: =IF(OR(I5="",K5=""),"",I5-K5) | M5: =IF(L5="","",L5-N5) | N5: =IF(L5="","",ROUND(L5/6,2)) | O5: =IF(OR(K5="",K5=0),"",M5/K5)
J6: =IF(I6="","",ROUND(I6/1.2,2)) | L6: =IF(OR(I6="",K6=""),"",I6-K6) | M6: =IF(L6="","",L6-N6) | N6: =IF(L6="","",ROUND(L6/6,2)) | O6: =IF(OR(K6="",K6=0),"",M6/K6)
J7: =IF(I7="","",ROUND(I7/1.2,2)) | L7: =IF(OR(I7="",K7=""),"",I7-K7) | M7: =IF(L7="","",L7-N7) | N7: =IF(L7="","",ROUND(L7/6,2)) | O7: =IF(OR(K7="",K7=0),"",M7/K7)
J8: =IF(I8="","",ROUND(I8/1.2,2)) | L8: =IF(OR(I8="",K8=""),"",I8-K8) | M8: =IF(L8="","",L8-N8) | N8: =IF(L8="","",ROUND(L8/6,2)) | O8: =IF(OR(K8="",K8=0),"",M8/K8)
J9: =IF(I9="","",ROUND(I9/1.2,2)) | L9: =IF(OR(I9="",K9=""),"",I9-K9) | M9: =IF(L9="","",L9-N9) | N9: =IF(L9="","",ROUND(L9/6,2)) | O9: =IF(OR(K9="",K9=0),"",M9/K9)
J10: =IF(I10="","",ROUND(I10/1.2,2)) | L10: =IF(OR(I10="",K10=""),"",I10-K10) | M10: =IF(L10="","",L10-N10) | N10: =IF(L10="","",ROUND(L10/6,2)) | O10: =IF(OR(K10="",K10=0),"",M10/K10)
J11: =IF(I11="","",ROUND(I11/1.2,2)) | L11: =IF(OR(I11="",K11=""),"",I11-K11) | M11: =IF(L11="","",L11-N11) | N11: =IF(L11="","",ROUND(L11/6,2)) | O11: =IF(OR(K11="",K11=0),"",M11/K11)
J12: =IF(I12="","",ROUND(I12/1.2,2)) | L12: =IF(OR(I12="",K12=""),"",I12-K12) | M12: =IF(L12="","",L12-N12) | N12: =IF(L12="","",ROUND(L12/6,2)) | O12: =IF(OR(K12="",K12=0),"",M12/K12)
J13: =IF(I13="","",ROUND(I13/1.2,2)) | L13: =IF(OR(I13="",K13=""),"",I13-K13) | M13: =IF(L13="","",L13-N13) | N13: =IF(L13="","",ROUND(L13/6,2)) | O13: =IF(OR(K13="",K13=0),"",M13/K13)
... J501: =IF(I501="","",ROUND(I501/1.2,2)) | L501: =IF(OR(I501="",K501=""),"",I501-K501) | M501: =IF(L501="","",L501-N501) | N501: =IF(L501="","",ROUND(L501/6,2)) | O501: =IF(OR(K501="",K501=0),"",M501/K501)

Sheet ADMINISTRATIF
A1: ID Dossier | B1: Immatriculation | C1: Marque / Modèle | D1: VIN | E1: Décl. Achat envoyée | F1: Date Décl. Achat | G1: CERFA Achat N° | H1: Décl. Cession envoyée | I1: CT Date Validité | J1: CT Résultat | K1: CT Avis | L1: CG Reçue | M1: CG Type | N1: CG Transmise Client | O1: Date Transmission CG | P1: STATUT DOSSIER | Q1: Documents Manquants | R1: Garantie (mois) | S1: Garantie Fin | T1: Notes Admin
S2: =IF(OR(R2="",R2=0),"",EDATE(TODAY(),R2))
S3: =IF(OR(R3="",R3=0),"",EDATE(TODAY(),R3))
S4: =IF(OR(R4="",R4=0),"",EDATE(TODAY(),R4))
S5: =IF(OR(R5="",R5=0),"",EDATE(TODAY(),R5))
S6: =IF(OR(R6="",R6=0),"",EDATE(TODAY(),R6))
S7: =IF(OR(R7="",R7=0),"",EDATE(TODAY(),R7))
S8: =IF(OR(R8="",R8=0),"",EDATE(TODAY(),R8))
S9: =IF(OR(R9="",R9=0),"",EDATE(TODAY(),R9))
S10: =IF(OR(R10="",R10=0),"",EDATE(TODAY(),R10))
S11: =IF(OR(R11="",R11=0),"",EDATE(TODAY(),R11))
S12: =IF(OR(R12="",R12=0),"",EDATE(TODAY(),R12))
S13: =IF(OR(R13="",R13=0),"",EDATE(TODAY(),R13))
... S501: =IF(OR(R501="",R501=0),"",EDATE(TODAY(),R501))

Sheet FINANCE
A1: 💰 SUIVI FINANCIER — Dépenses & Rentabilité | N1: 📊 RÉCAPITULATIF MENSUEL
A2: Date | B2: Catégorie | C2: Sous-catégorie | D2: Description | E2: Montant HT | F2: TVA | G2: Montant TTC | H2: Mode Paiement | I2: Référence | J2: Mois | K2: Année | L2: Notes
F3: =IF(E3="","",ROUND(E3*0.2,2)) | G3: =IF(E3="","",E3+F3) | J3: =IF(A3="","",MONTH(A3)) | K3: =IF(A3="","",YEAR(A3)) | N3: CA Mensuel | O3: =SUMPRODUCT((VENTES!E2:E5001>=DATE(YEAR(TODAY()),MONTH(TODAY()),1))*(VENTES!E2:E5001<=EOMONTH(TODAY(),0))*(VENTES!I2:I5001)) -> 0
F4: =IF(E4="","",ROUND(E4*0.2,2)) | G4: =IF(E4="","",E4+F4) | J4: =IF(A4="","",MONTH(A4)) | K4: =IF(A4="","",YEAR(A4)) | N4: Achats Véhicules | O4: =IFERROR(SUMPRODUCT((FINANCE!J3:J502=MONTH(TODAY()))*(FINANCE!K3:K502=YEAR(TODAY()))*(FINANCE!B3:B502="Achats véhicules")*(FINANCE!G3:G502)),0) -> 0
F5: =IF(E5="","",ROUND(E5*0.2,2)) | G5: =IF(E5="","",E5+F5) | J5: =IF(A5="","",MONTH(A5)) | K5: =IF(A5="","",YEAR(A5)) | N5: Réparations | O5: =IFERROR(SUMPRODUCT((FINANCE!J3:J502=MONTH(TODAY()))*(FINANCE!K3:K502=YEAR(TODAY()))*(FINANCE!B3:B502="Réparations")*(FINANCE!G3:G502)),0) -> 0
F6: =IF(E6="","",ROUND(E6*0.2,2)) | G6: =IF(E6="","",E6+F6) | J6: =IF(A6="","",MONTH(A6)) | K6: =IF(A6="","",YEAR(A6)) | N6: Publicité | O6: =IFERROR(SUMPRODUCT((FINANCE!J3:J502=MONTH(TODAY()))*(FINANCE!K3:K502=YEAR(TODAY()))*(FINANCE!B3:B502="Publicité")*(FINANCE!G3:G502)),0) -> 0
F7: =IF(E7="","",ROUND(E7*0.2,2)) | G7: =IF(E7="","",E7+F7) | J7: =IF(A7="","",MONTH(A7)) | K7: =IF(A7="","",YEAR(A7)) | N7: Frais Fixes | O7: =IFERROR(SUMPRODUCT((FINANCE!J3:J502=MONTH(TODAY()))*(FINANCE!K3:K502=YEAR(TODAY()))*(FINANCE!B3:B502="Loyer")*(FINANCE!G3:G502)),0)+IFERROR(SUMPRODUCT((FINANCE!J3:J502=MONTH(TODAY()))*(FINANCE!K3:K502=YEAR(TODAY()))*(FINANCE!B3:B502="Assurance")*(FINANCE!G3:G502)),0) -> 0
F8: =IF(E8="","",ROUND(E8*0.2,2)) | G8: =IF(E8="","",E8+F8) | J8: =IF(A8="","",MONTH(A8)) | K8: =IF(A8="","",YEAR(A8)) | N8: Salaires | O8: =IFERROR(SUMPRODUCT((FINANCE!J3:J502=MONTH(TODAY()))*(FINANCE!K3:K502=YEAR(TODAY()))*(FINANCE!B3:B502="Salaires")*(FINANCE!G3:G502)),0) -> 0
F9: =IF(E9="","",ROUND(E9*0.2,2)) | G9: =IF(E9="","",E9+F9) | J9: =IF(A9="","",MONTH(A9)) | K9: =IF(A9="","",YEAR(A9)) | N9: Transport | O9: =IFERROR(SUMPRODUCT((FINANCE!J3:J502=MONTH(TODAY()))*(FINANCE!K3:K502=YEAR(TODAY()))*(FINANCE!B3:B502="Transport")*(FINANCE!G3:G502)),0) -> 0
F10: =IF(E10="","",ROUND(E10*0.2,2)) | G10: =IF(E10="","",E10+F10) | J10: =IF(A10="","",MONTH(A10)) | K10: =IF(A10="","",YEAR(A10)) | N10: Autres | O10: =IFERROR(SUMPRODUCT((FINANCE!J3:J502=MONTH(TODAY()))*(FINANCE!K3:K502=YEAR(TODAY()))*(FINANCE!G3:G502)),0)-O4-O5-O6-O7-O8-O9 -> 0
F11: =IF(E11="","",ROUND(E11*0.2,2)) | G11: =IF(E11="","",E11+F11) | J11: =IF(A11="","",MONTH(A11)) | K11: =IF(A11="","",YEAR(A11)) | N11: TOTAL DÉPENSES | O11: =SUM(O4:O10) -> 0
F12: =IF(E12="","",ROUND(E12*0.2,2)) | G12: =IF(E12="","",E12+F12) | J12: =IF(A12="","",MONTH(A12)) | K12: =IF(A12="","",YEAR(A12)) | N12: BÉNÉFICE NET | O12: =O3-O11 -> 0
F13: =IF(E13="","",ROUND(E13*0.2,2)) | G13: =IF(E13="","",E13+F13) | J13: =IF(A13="","",MONTH(A13)) | K13: =IF(A13="","",YEAR(A13))
F14: =IF(E14="","",ROUND(E14*0.2,2)) | G14: =IF(E14="","",E14+F14) | J14: =IF(A14="","",MONTH(A14)) | K14: =IF(A14="","",YEAR(A14))
F15: =IF(E15="","",ROUND(E15*0.2,2)) | G15: =IF(E15="","",E15+F15) | J15: =IF(A15="","",MONTH(A15)) | K15: =IF(A15="","",YEAR(A15))
F16: =IF(E16="","",ROUND(E16*0.2,2)) | G16: =IF(E16="","",E16+F16) | J16: =IF(A16="","",MONTH(A16)) | K16: =IF(A16="","",YEAR(A16))
F17: =IF(E17="","",ROUND(E17*0.2,2)) | G17: =IF(E17="","",E17+F17) | J17: =IF(A17="","",MONTH(A17)) | K17: =IF(A17="","",YEAR(A17))
F18: =IF(E18="","",ROUND(E18*0.2,2)) | G18: =IF(E18="","",E18+F18) | J18: =IF(A18="","",MONTH(A18)) | K18: =IF(A18="","",YEAR(A18))
F19: =IF(E19="","",ROUND(E19*0.2,2)) | G19: =IF(E19="","",E19+F19) | J19: =IF(A19="","",MONTH(A19)) | K19: =IF(A19="","",YEAR(A19))
F20: =IF(E20="","",ROUND(E20*0.2,2)) | G20: =IF(E20="","",E20+F20) | J20: =IF(A20="","",MONTH(A20)) | K20: =IF(A20="","",YEAR(A20))
F21: =IF(E21="","",ROUND(E21*0.2,2)) | G21: =IF(E21="","",E21+F21) | J21: =IF(A21="","",MONTH(A21)) | K21: =IF(A21="","",YEAR(A21))
F22: =IF(E22="","",ROUND(E22*0.2,2)) | G22: =IF(E22="","",E22+F22) | J22: =IF(A22="","",MONTH(A22)) | K22: =IF(A22="","",YEAR(A22))
F23: =IF(E23="","",ROUND(E23*0.2,2)) | G23: =IF(E23="","",E23+F23) | J23: =IF(A23="","",MONTH(A23)) | K23: =IF(A23="","",YEAR(A23))
F24: =IF(E24="","",ROUND(E24*0.2,2)) | G24: =IF(E24="","",E24+F24) | J24: =IF(A24="","",MONTH(A24)) | K24: =IF(A24="","",YEAR(A24))
... F502: =IF(E502="","",ROUND(E502*0.2,2)) | G502: =IF(E502="","",E502+F502) | J502: =IF(A502="","",MONTH(A502)) | K502: =IF(A502="","",YEAR(A502))

Sheet BON DE COMMANDE
B2: NOM DU GARAGE | E2: BON DE COMMANDE N° BC-XXXX
B3: Adresse — Ville | Tél : XX XX XX XX XX | SIRET : XXX
B4: BON DE COMMANDE VÉHICULE D'OCCASION
B6: 👤 ACHETEUR | D6: 🚗 VÉHICULE
B7: Nom / Prénom : | D7: Marque / Modèle :
B8: Adresse : | D8: Immatriculation :
B9: Téléphone : | D9: VIN :
D10: Année / Km :
D11: Version :
B16: 💰 CONDITIONS FINANCIÈRES
B17: Prix de vente TTC
B18: Dont TVA sur marge
B19: Acompte versé
B20: SOLDE À RÉGLER
B23: Le présent bon de commande est établi conformément aux dispositions légales. TVA calculée sur la marge, art. 297A du CGI. Garantie légale de conformité et vices cachés applicable.
B25: Signature Vendeur : _______________________ | D25: Signature Acheteur (Lu et approuvé) : _______________________

Sheet PARAMÈTRES
B1: ⚙️ PARAMÈTRES SpiderVO Pro
B3: IDENTITÉ GARAGE
B4: Nom du garage | C4: Mon Garage VO
B5: SIRET
B6: TVA intracommunautaire
B7: Adresse
B8: Code Postal
B9: Ville
B10: Téléphone
B11: Email
B12: Site web
B14: ÉQUIPE COMMERCIALE
B15: Vendeur 1
B16: Vendeur 2
B17: Vendeur 3
B19: PARAMÈTRES SYSTÈME
B20: Marge minimum (%) | C20: 8
B21: Seuil véhicule dormant (j) | C21: 45
B22: Email notifications
B23: Objectif CA mensuel (€)
B24: Devise | C24: EUR

Sheet 📖 GUIDE
B1: 📖 GUIDE D'UTILISATION — SpiderVO Pro
B3: ONGLETS DU SYSTÈME
B5: DASHBOARD | C5: Vue d'ensemble : KPIs stock, ventes du mois, alertes. Se met à jour automatiquement.
B6: STOCK VO | C6: Saisir chaque véhicule acheté. Les colonnes AF→AN (coût revient, marges, ROI) se calculent seules.
B7: CRM CLIENTS | C7: Suivi leads et clients. Pipeline de vente, score chaud/froid, relances. Mettre à jour 'Dernier Contact'.
B8: VENTES | C8: Enregistrer chaque vente. TVA marge calculée auto. Lier à l'ID Dossier VO correspondant.
B9: ADMINISTRATIF | C9: Suivi CERFA, carte grise, CT, garanties. Statut dossier = ✅ COMPLET / ⚠️ INCOMPLET / ❌ BLOQUANT.
B10: FINANCE | C10: Toutes les dépenses du garage. Le récapitulatif mensuel (colonnes N-O) se calcule automatiquement.
B11: BON DE COMMANDE | C11: Template à remplir et imprimer (Ctrl+P) ou exporter en PDF (Fichier > Exporter).
B12: PARAMÈTRES | C12: Saisir les infos du garage UNE SEULE FOIS. Ces données alimentent les documents.
B13: FORMULES CLÉS
B15: Coût de Revient | C15: =prix achat + transport + réparations + nettoyage + carte grise + préparation + divers
B16: Marge Brute | C16: =prix affiché - coût de revient
B17: TVA sur Marge | C17: =(prix vente ttc - prix achat ttc) / 1.2 × 0.20 [Régime de la marge]
B18: Marge Nette | C18: =marge brute - tva sur marge
B19: ROI | C19: =marge nette / coût de revient
B20: CONSEILS PRO
B22: Alerte dormants | C22: Tout véhicule en stock >45 jours est signalé en jaune (colonne AR). Baisser le prix ou changer la diffusion.
B23: Score CRM | C23: Mettre à jour le score (🔥 Chaud) après chaque contact. Prioriser les relances chauds.
B24: CERFA | C24: Renseigner ADMINISTRATIF dès l'achat. Compléter la déclaration de cession dans les 15 jours de la vente.
B25: Sauvegarde | C25: Dupliquer le fichier chaque semaine (Fichier > Créer une copie) dans un dossier Drive dédié.
B26: Sécurité | C26: Protéger les colonnes de formules (AF:AN dans STOCK VO) via Format > Protéger la plage.
